{
    "cod": "200",
    "message": 0,
    "cnt": 40,
    "list": [
        {
            "dt": 1712674800,
            "main": {
                "temp": 75.78,
                "feels_like": 76.1,
                "temp_min": 75,
                "temp_max": 75.78,
                "pressure": 1020,
                "sea_level": 1020,
                "grnd_level": 1020,
                "humidity": 65,
                "temp_kf": 0.43
            },
            "weather": [
                {
                    "id": 500,
                    "main": "Rain",
                    "description": "light rain",
                    "icon": "10d"
                }
            ],
            "clouds": {
                "all": 75
            },
            "wind": {
                "speed": 17.4,
                "deg": 115,
                "gust": 19.69
            },
            "visibility": 10000,
            "pop": 0.2,
            "rain": {
                "3h": 0.12
            },
            "sys": {
                "pod": "d"
            },
            "dt_txt": "2024-04-09 15:00:00"
        },
        {
            "dt": 1712685600,
            "main": {
                "temp": 76.3,
                "feels_like": 76.5,
                "temp_min": 76.3,
                "temp_max": 77.36,
                "pressure": 1020,
                "sea_level": 1020,
                "grnd_level": 1019,
                "humidity": 61,
                "temp_kf": -0.59
            },
            "weather": [
                {
                    "id": 500,
                    "main": "Rain",
                    "description": "light rain",
                    "icon": "10d"
                }
            ],
            "clouds": {
                "all": 80
            },
            "wind": {
                "speed": 16.44,
                "deg": 116,
                "gust": 17.74
            },
            "visibility": 10000,
            "pop": 0.2,
            "rain": {
                "3h": 0.12
            },
            "sys": {
                "pod": "d"
            },
            "dt_txt": "2024-04-09 18:00:00"
        },
        {
            "dt": 1712696400,
            "main": {
                "temp": 75.9,
                "feels_like": 76.06,
                "temp_min": 75.9,
                "temp_max": 75.96,
                "pressure": 1019,
                "sea_level": 1019,
                "grnd_level": 1017,
                "humidity": 61,
                "temp_kf": -0.03
            },
            "weather": [
                {
                    "id": 803,
                    "main": "Clouds",
                    "description": "broken clouds",
                    "icon": "04d"
                }
            ],
            "clouds": {
                "all": 73
            },
            "wind": {
                "speed": 16.11,
                "deg": 111,
                "gust": 17.56
            },
            "visibility": 10000,
            "pop": 0,
            "sys": {
                "pod": "d"
            },
            "dt_txt": "2024-04-09 21:00:00"
        },
        {
            "dt": 1712707200,
            "main": {
                "temp": 74.88,
                "feels_like": 75.07,
                "temp_min": 74.88,
                "temp_max": 74.88,
                "pressure": 1018,
                "sea_level": 1018,
                "grnd_level": 1017,
                "humidity": 64,
                "temp_kf": 0
            },
            "weather": [
                {
                    "id": 804,
                    "main": "Clouds",
                    "description": "overcast clouds",
                    "icon": "04n"
                }
            ],
            "clouds": {
                "all": 86
            },
            "wind": {
                "speed": 18.19,
                "deg": 105,
                "gust": 19.82
            },
            "visibility": 10000,
            "pop": 0,
            "sys": {
                "pod": "n"
            },
            "dt_txt": "2024-04-10 00:00:00"
        },
        {
            "dt": 1712718000,
            "main": {
                "temp": 74.57,
                "feels_like": 74.82,
                "temp_min": 74.57,
                "temp_max": 74.57,
                "pressure": 1018,
                "sea_level": 1018,
                "grnd_level": 1018,
                "humidity": 66,
                "temp_kf": 0
            },
            "weather": [
                {
                    "id": 804,
                    "main": "Clouds",
                    "description": "overcast clouds",
                    "icon": "04n"
                }
            ],
            "clouds": {
                "all": 99
            },
            "wind": {
                "speed": 19.28,
                "deg": 104,
                "gust": 21.94
            },
            "visibility": 10000,
            "pop": 0,
            "sys": {
                "pod": "n"
            },
            "dt_txt": "2024-04-10 03:00:00"
        },
        {
            "dt": 1712728800,
            "main": {
                "temp": 74.17,
                "feels_like": 74.3,
                "temp_min": 74.17,
                "temp_max": 74.17,
                "pressure": 1017,
                "sea_level": 1017,
                "grnd_level": 1016,
                "humidity": 64,
                "temp_kf": 0
            },
            "weather": [
                {
                    "id": 803,
                    "main": "Clouds",
                    "description": "broken clouds",
                    "icon": "04n"
                }
            ],
            "clouds": {
                "all": 84
            },
            "wind": {
                "speed": 17.05,
                "deg": 121,
                "gust": 20.36
            },
            "visibility": 10000,
            "pop": 0,
            "sys": {
                "pod": "n"
            },
            "dt_txt": "2024-04-10 06:00:00"
        },
        {
            "dt": 1712739600,
            "main": {
                "temp": 74.26,
                "feels_like": 74.16,
                "temp_min": 74.26,
                "temp_max": 74.26,
                "pressure": 1017,
                "sea_level": 1017,
                "grnd_level": 1016,
                "humidity": 59,
                "temp_kf": 0
            },
            "weather": [
                {
                    "id": 802,
                    "main": "Clouds",
                    "description": "scattered clouds",
                    "icon": "03n"
                }
            ],
            "clouds": {
                "all": 47
            },
            "wind": {
                "speed": 13.42,
                "deg": 127,
                "gust": 16.49
            },
            "visibility": 10000,
            "pop": 0,
            "sys": {
                "pod": "n"
            },
            "dt_txt": "2024-04-10 09:00:00"
        },
        {
            "dt": 1712750400,
            "main": {
                "temp": 75.15,
                "feels_like": 75.13,
                "temp_min": 75.15,
                "temp_max": 75.15,
                "pressure": 1017,
                "sea_level": 1017,
                "grnd_level": 1016,
                "humidity": 59,
                "temp_kf": 0
            },
            "weather": [
                {
                    "id": 803,
                    "main": "Clouds",
                    "description": "broken clouds",
                    "icon": "04d"
                }
            ],
            "clouds": {
                "all": 73
            },
            "wind": {
                "speed": 14.32,
                "deg": 133,
                "gust": 16.37
            },
            "visibility": 10000,
            "pop": 0,
            "sys": {
                "pod": "d"
            },
            "dt_txt": "2024-04-10 12:00:00"
        },
        {
            "dt": 1712761200,
            "main": {
                "temp": 76.55,
                "feels_like": 76.77,
                "temp_min": 76.55,
                "temp_max": 76.55,
                "pressure": 1018,
                "sea_level": 1018,
                "grnd_level": 1017,
                "humidity": 61,
                "temp_kf": 0
            },
            "weather": [
                {
                    "id": 804,
                    "main": "Clouds",
                    "description": "overcast clouds",
                    "icon": "04d"
                }
            ],
            "clouds": {
                "all": 100
            },
            "wind": {
                "speed": 16.84,
                "deg": 127,
                "gust": 16.42
            },
            "visibility": 10000,
            "pop": 0,
            "sys": {
                "pod": "d"
            },
            "dt_txt": "2024-04-10 15:00:00"
        },
        {
            "dt": 1712772000,
            "main": {
                "temp": 77.09,
                "feels_like": 77.36,
                "temp_min": 77.09,
                "temp_max": 77.09,
                "pressure": 1016,
                "sea_level": 1016,
                "grnd_level": 1016,
                "humidity": 61,
                "temp_kf": 0
            },
            "weather": [
                {
                    "id": 804,
                    "main": "Clouds",
                    "description": "overcast clouds",
                    "icon": "04d"
                }
            ],
            "clouds": {
                "all": 98
            },
            "wind": {
                "speed": 16.62,
                "deg": 129,
                "gust": 15.9
            },
            "visibility": 10000,
            "pop": 0,
            "sys": {
                "pod": "d"
            },
            "dt_txt": "2024-04-10 18:00:00"
        },
        {
            "dt": 1712782800,
            "main": {
                "temp": 78.19,
                "feels_like": 78.39,
                "temp_min": 78.19,
                "temp_max": 78.19,
                "pressure": 1015,
                "sea_level": 1015,
                "grnd_level": 1014,
                "humidity": 57,
                "temp_kf": 0
            },
            "weather": [
                {
                    "id": 804,
                    "main": "Clouds",
                    "description": "overcast clouds",
                    "icon": "04d"
                }
            ],
            "clouds": {
                "all": 98
            },
            "wind": {
                "speed": 13.35,
                "deg": 131,
                "gust": 13.56
            },
            "visibility": 10000,
            "pop": 0,
            "sys": {
                "pod": "d"
            },
            "dt_txt": "2024-04-10 21:00:00"
        },
        {
            "dt": 1712793600,
            "main": {
                "temp": 76.62,
                "feels_like": 77.04,
                "temp_min": 76.62,
                "temp_max": 76.62,
                "pressure": 1016,
                "sea_level": 1016,
                "grnd_level": 1015,
                "humidity": 65,
                "temp_kf": 0
            },
            "weather": [
                {
                    "id": 803,
                    "main": "Clouds",
                    "description": "broken clouds",
                    "icon": "04n"
                }
            ],
            "clouds": {
                "all": 70
            },
            "wind": {
                "speed": 10.98,
                "deg": 123,
                "gust": 17.52
            },
            "visibility": 10000,
            "pop": 0,
            "sys": {
                "pod": "n"
            },
            "dt_txt": "2024-04-11 00:00:00"
        },
        {
            "dt": 1712804400,
            "main": {
                "temp": 76.42,
                "feels_like": 77.05,
                "temp_min": 76.42,
                "temp_max": 76.42,
                "pressure": 1016,
                "sea_level": 1016,
                "grnd_level": 1015,
                "humidity": 70,
                "temp_kf": 0
            },
            "weather": [
                {
                    "id": 804,
                    "main": "Clouds",
                    "description": "overcast clouds",
                    "icon": "04n"
                }
            ],
            "clouds": {
                "all": 100
            },
            "wind": {
                "speed": 11.45,
                "deg": 111,
                "gust": 17.72
            },
            "visibility": 10000,
            "pop": 0,
            "sys": {
                "pod": "n"
            },
            "dt_txt": "2024-04-11 03:00:00"
        },
        {
            "dt": 1712815200,
            "main": {
                "temp": 75.76,
                "feels_like": 76.51,
                "temp_min": 75.76,
                "temp_max": 75.76,
                "pressure": 1015,
                "sea_level": 1015,
                "grnd_level": 1014,
                "humidity": 74,
                "temp_kf": 0
            },
            "weather": [
                {
                    "id": 804,
                    "main": "Clouds",
                    "description": "overcast clouds",
                    "icon": "04n"
                }
            ],
            "clouds": {
                "all": 99
            },
            "wind": {
                "speed": 17.94,
                "deg": 139,
                "gust": 21.72
            },
            "visibility": 10000,
            "pop": 0,
            "sys": {
                "pod": "n"
            },
            "dt_txt": "2024-04-11 06:00:00"
        },
        {
            "dt": 1712826000,
            "main": {
                "temp": 75.42,
                "feels_like": 76.23,
                "temp_min": 75.42,
                "temp_max": 75.42,
                "pressure": 1015,
                "sea_level": 1015,
                "grnd_level": 1014,
                "humidity": 76,
                "temp_kf": 0
            },
            "weather": [
                {
                    "id": 802,
                    "main": "Clouds",
                    "description": "scattered clouds",
                    "icon": "03n"
                }
            ],
            "clouds": {
                "all": 40
            },
            "wind": {
                "speed": 16.11,
                "deg": 149,
                "gust": 21.47
            },
            "visibility": 10000,
            "pop": 0,
            "sys": {
                "pod": "n"
            },
            "dt_txt": "2024-04-11 09:00:00"
        },
        {
            "dt": 1712836800,
            "main": {
                "temp": 76.17,
                "feels_like": 77.11,
                "temp_min": 76.17,
                "temp_max": 76.17,
                "pressure": 1015,
                "sea_level": 1015,
                "grnd_level": 1015,
                "humidity": 77,
                "temp_kf": 0
            },
            "weather": [
                {
                    "id": 801,
                    "main": "Clouds",
                    "description": "few clouds",
                    "icon": "02d"
                }
            ],
            "clouds": {
                "all": 22
            },
            "wind": {
                "speed": 15.68,
                "deg": 157,
                "gust": 21.32
            },
            "visibility": 10000,
            "pop": 0,
            "sys": {
                "pod": "d"
            },
            "dt_txt": "2024-04-11 12:00:00"
        },
        {
            "dt": 1712847600,
            "main": {
                "temp": 80.29,
                "feels_like": 83.43,
                "temp_min": 80.29,
                "temp_max": 80.29,
                "pressure": 1015,
                "sea_level": 1015,
                "grnd_level": 1015,
                "humidity": 70,
                "temp_kf": 0
            },
            "weather": [
                {
                    "id": 801,
                    "main": "Clouds",
                    "description": "few clouds",
                    "icon": "02d"
                }
            ],
            "clouds": {
                "all": 15
            },
            "wind": {
                "speed": 19.26,
                "deg": 162,
                "gust": 22.7
            },
            "visibility": 10000,
            "pop": 0,
            "sys": {
                "pod": "d"
            },
            "dt_txt": "2024-04-11 15:00:00"
        },
        {
            "dt": 1712858400,
            "main": {
                "temp": 83.21,
                "feels_like": 87.22,
                "temp_min": 83.21,
                "temp_max": 83.21,
                "pressure": 1015,
                "sea_level": 1015,
                "grnd_level": 1014,
                "humidity": 64,
                "temp_kf": 0
            },
            "weather": [
                {
                    "id": 802,
                    "main": "Clouds",
                    "description": "scattered clouds",
                    "icon": "03d"
                }
            ],
            "clouds": {
                "all": 33
            },
            "wind": {
                "speed": 18.21,
                "deg": 171,
                "gust": 21.61
            },
            "visibility": 10000,
            "pop": 0,
            "sys": {
                "pod": "d"
            },
            "dt_txt": "2024-04-11 18:00:00"
        },
        {
            "dt": 1712869200,
            "main": {
                "temp": 84.38,
                "feels_like": 86.83,
                "temp_min": 84.38,
                "temp_max": 84.38,
                "pressure": 1014,
                "sea_level": 1014,
                "grnd_level": 1013,
                "humidity": 55,
                "temp_kf": 0
            },
            "weather": [
                {
                    "id": 803,
                    "main": "Clouds",
                    "description": "broken clouds",
                    "icon": "04d"
                }
            ],
            "clouds": {
                "all": 64
            },
            "wind": {
                "speed": 17.65,
                "deg": 188,
                "gust": 19.93
            },
            "visibility": 10000,
            "pop": 0,
            "sys": {
                "pod": "d"
            },
            "dt_txt": "2024-04-11 21:00:00"
        },
        {
            "dt": 1712880000,
            "main": {
                "temp": 80.38,
                "feels_like": 83.59,
                "temp_min": 80.38,
                "temp_max": 80.38,
                "pressure": 1015,
                "sea_level": 1015,
                "grnd_level": 1015,
                "humidity": 70,
                "temp_kf": 0
            },
            "weather": [
                {
                    "id": 803,
                    "main": "Clouds",
                    "description": "broken clouds",
                    "icon": "04n"
                }
            ],
            "clouds": {
                "all": 82
            },
            "wind": {
                "speed": 12.06,
                "deg": 174,
                "gust": 13.89
            },
            "visibility": 10000,
            "pop": 0,
            "sys": {
                "pod": "n"
            },
            "dt_txt": "2024-04-12 00:00:00"
        },
        {
            "dt": 1712890800,
            "main": {
                "temp": 77.94,
                "feels_like": 79.23,
                "temp_min": 77.94,
                "temp_max": 77.94,
                "pressure": 1017,
                "sea_level": 1017,
                "grnd_level": 1016,
                "humidity": 81,
                "temp_kf": 0
            },
            "weather": [
                {
                    "id": 802,
                    "main": "Clouds",
                    "description": "scattered clouds",
                    "icon": "03n"
                }
            ],
            "clouds": {
                "all": 32
            },
            "wind": {
                "speed": 10.8,
                "deg": 182,
                "gust": 16.04
            },
            "visibility": 10000,
            "pop": 0,
            "sys": {
                "pod": "n"
            },
            "dt_txt": "2024-04-12 03:00:00"
        },
        {
            "dt": 1712901600,
            "main": {
                "temp": 77.29,
                "feels_like": 78.53,
                "temp_min": 77.29,
                "temp_max": 77.29,
                "pressure": 1017,
                "sea_level": 1017,
                "grnd_level": 1016,
                "humidity": 81,
                "temp_kf": 0
            },
            "weather": [
                {
                    "id": 500,
                    "main": "Rain",
                    "description": "light rain",
                    "icon": "10n"
                }
            ],
            "clouds": {
                "all": 31
            },
            "wind": {
                "speed": 9.75,
                "deg": 228,
                "gust": 18.12
            },
            "visibility": 10000,
            "pop": 0.2,
            "rain": {
                "3h": 0.24
            },
            "sys": {
                "pod": "n"
            },
            "dt_txt": "2024-04-12 06:00:00"
        },
        {
            "dt": 1712912400,
            "main": {
                "temp": 74.98,
                "feels_like": 75.38,
                "temp_min": 74.98,
                "temp_max": 74.98,
                "pressure": 1017,
                "sea_level": 1017,
                "grnd_level": 1017,
                "humidity": 68,
                "temp_kf": 0
            },
            "weather": [
                {
                    "id": 804,
                    "main": "Clouds",
                    "description": "overcast clouds",
                    "icon": "04n"
                }
            ],
            "clouds": {
                "all": 98
            },
            "wind": {
                "speed": 12.44,
                "deg": 316,
                "gust": 15.19
            },
            "visibility": 10000,
            "pop": 0,
            "sys": {
                "pod": "n"
            },
            "dt_txt": "2024-04-12 09:00:00"
        },
        {
            "dt": 1712923200,
            "main": {
                "temp": 72.39,
                "feels_like": 72.43,
                "temp_min": 72.39,
                "temp_max": 72.39,
                "pressure": 1020,
                "sea_level": 1020,
                "grnd_level": 1019,
                "humidity": 66,
                "temp_kf": 0
            },
            "weather": [
                {
                    "id": 803,
                    "main": "Clouds",
                    "description": "broken clouds",
                    "icon": "04d"
                }
            ],
            "clouds": {
                "all": 67
            },
            "wind": {
                "speed": 14.97,
                "deg": 336,
                "gust": 15.48
            },
            "visibility": 10000,
            "pop": 0,
            "sys": {
                "pod": "d"
            },
            "dt_txt": "2024-04-12 12:00:00"
        },
        {
            "dt": 1712934000,
            "main": {
                "temp": 76.8,
                "feels_like": 76.3,
                "temp_min": 76.8,
                "temp_max": 76.8,
                "pressure": 1021,
                "sea_level": 1021,
                "grnd_level": 1020,
                "humidity": 45,
                "temp_kf": 0
            },
            "weather": [
                {
                    "id": 801,
                    "main": "Clouds",
                    "description": "few clouds",
                    "icon": "02d"
                }
            ],
            "clouds": {
                "all": 20
            },
            "wind": {
                "speed": 9.69,
                "deg": 347,
                "gust": 10.22
            },
            "visibility": 10000,
            "pop": 0,
            "sys": {
                "pod": "d"
            },
            "dt_txt": "2024-04-12 15:00:00"
        },
        {
            "dt": 1712944800,
            "main": {
                "temp": 81.55,
                "feels_like": 80.78,
                "temp_min": 81.55,
                "temp_max": 81.55,
                "pressure": 1020,
                "sea_level": 1020,
                "grnd_level": 1019,
                "humidity": 37,
                "temp_kf": 0
            },
            "weather": [
                {
                    "id": 801,
                    "main": "Clouds",
                    "description": "few clouds",
                    "icon": "02d"
                }
            ],
            "clouds": {
                "all": 18
            },
            "wind": {
                "speed": 5.68,
                "deg": 44,
                "gust": 7.05
            },
            "visibility": 10000,
            "pop": 0,
            "sys": {
                "pod": "d"
            },
            "dt_txt": "2024-04-12 18:00:00"
        },
        {
            "dt": 1712955600,
            "main": {
                "temp": 79.43,
                "feels_like": 79.43,
                "temp_min": 79.43,
                "temp_max": 79.43,
                "pressure": 1019,
                "sea_level": 1019,
                "grnd_level": 1018,
                "humidity": 40,
                "temp_kf": 0
            },
            "weather": [
                {
                    "id": 800,
                    "main": "Clear",
                    "description": "clear sky",
                    "icon": "01d"
                }
            ],
            "clouds": {
                "all": 7
            },
            "wind": {
                "speed": 10.71,
                "deg": 79,
                "gust": 8.1
            },
            "visibility": 10000,
            "pop": 0,
            "sys": {
                "pod": "d"
            },
            "dt_txt": "2024-04-12 21:00:00"
        },
        {
            "dt": 1712966400,
            "main": {
                "temp": 75.38,
                "feels_like": 75.02,
                "temp_min": 75.38,
                "temp_max": 75.38,
                "pressure": 1021,
                "sea_level": 1021,
                "grnd_level": 1020,
                "humidity": 51,
                "temp_kf": 0
            },
            "weather": [
                {
                    "id": 800,
                    "main": "Clear",
                    "description": "clear sky",
                    "icon": "01n"
                }
            ],
            "clouds": {
                "all": 6
            },
            "wind": {
                "speed": 9.66,
                "deg": 87,
                "gust": 8.68
            },
            "visibility": 10000,
            "pop": 0,
            "sys": {
                "pod": "n"
            },
            "dt_txt": "2024-04-13 00:00:00"
        },
        {
            "dt": 1712977200,
            "main": {
                "temp": 74.55,
                "feels_like": 74.16,
                "temp_min": 74.55,
                "temp_max": 74.55,
                "pressure": 1022,
                "sea_level": 1022,
                "grnd_level": 1022,
                "humidity": 52,
                "temp_kf": 0
            },
            "weather": [
                {
                    "id": 800,
                    "main": "Clear",
                    "description": "clear sky",
                    "icon": "01n"
                }
            ],
            "clouds": {
                "all": 4
            },
            "wind": {
                "speed": 3.27,
                "deg": 93,
                "gust": 3.02
            },
            "visibility": 10000,
            "pop": 0,
            "sys": {
                "pod": "n"
            },
            "dt_txt": "2024-04-13 03:00:00"
        },
        {
            "dt": 1712988000,
            "main": {
                "temp": 73.58,
                "feels_like": 72.7,
                "temp_min": 73.58,
                "temp_max": 73.58,
                "pressure": 1022,
                "sea_level": 1022,
                "grnd_level": 1021,
                "humidity": 44,
                "temp_kf": 0
            },
            "weather": [
                {
                    "id": 800,
                    "main": "Clear",
                    "description": "clear sky",
                    "icon": "01n"
                }
            ],
            "clouds": {
                "all": 4
            },
            "wind": {
                "speed": 11.12,
                "deg": 340,
                "gust": 11.83
            },
            "visibility": 10000,
            "pop": 0,
            "sys": {
                "pod": "n"
            },
            "dt_txt": "2024-04-13 06:00:00"
        },
        {
            "dt": 1712998800,
            "main": {
                "temp": 70.11,
                "feels_like": 69.12,
                "temp_min": 70.11,
                "temp_max": 70.11,
                "pressure": 1022,
                "sea_level": 1022,
                "grnd_level": 1021,
                "humidity": 49,
                "temp_kf": 0
            },
            "weather": [
                {
                    "id": 800,
                    "main": "Clear",
                    "description": "clear sky",
                    "icon": "01n"
                }
            ],
            "clouds": {
                "all": 4
            },
            "wind": {
                "speed": 13.76,
                "deg": 357,
                "gust": 18.1
            },
            "visibility": 10000,
            "pop": 0,
            "sys": {
                "pod": "n"
            },
            "dt_txt": "2024-04-13 09:00:00"
        },
        {
            "dt": 1713009600,
            "main": {
                "temp": 69.82,
                "feels_like": 68.76,
                "temp_min": 69.82,
                "temp_max": 69.82,
                "pressure": 1023,
                "sea_level": 1023,
                "grnd_level": 1023,
                "humidity": 48,
                "temp_kf": 0
            },
            "weather": [
                {
                    "id": 800,
                    "main": "Clear",
                    "description": "clear sky",
                    "icon": "01d"
                }
            ],
            "clouds": {
                "all": 3
            },
            "wind": {
                "speed": 10.18,
                "deg": 20,
                "gust": 13.62
            },
            "visibility": 10000,
            "pop": 0,
            "sys": {
                "pod": "d"
            },
            "dt_txt": "2024-04-13 12:00:00"
        },
        {
            "dt": 1713020400,
            "main": {
                "temp": 76.14,
                "feels_like": 75.79,
                "temp_min": 76.14,
                "temp_max": 76.14,
                "pressure": 1024,
                "sea_level": 1024,
                "grnd_level": 1023,
                "humidity": 50,
                "temp_kf": 0
            },
            "weather": [
                {
                    "id": 800,
                    "main": "Clear",
                    "description": "clear sky",
                    "icon": "01d"
                }
            ],
            "clouds": {
                "all": 7
            },
            "wind": {
                "speed": 12.24,
                "deg": 51,
                "gust": 12.39
            },
            "visibility": 10000,
            "pop": 0,
            "sys": {
                "pod": "d"
            },
            "dt_txt": "2024-04-13 15:00:00"
        },
        {
            "dt": 1713031200,
            "main": {
                "temp": 78.51,
                "feels_like": 78.13,
                "temp_min": 78.51,
                "temp_max": 78.51,
                "pressure": 1023,
                "sea_level": 1023,
                "grnd_level": 1022,
                "humidity": 44,
                "temp_kf": 0
            },
            "weather": [
                {
                    "id": 800,
                    "main": "Clear",
                    "description": "clear sky",
                    "icon": "01d"
                }
            ],
            "clouds": {
                "all": 8
            },
            "wind": {
                "speed": 13.85,
                "deg": 66,
                "gust": 13.11
            },
            "visibility": 10000,
            "pop": 0,
            "sys": {
                "pod": "d"
            },
            "dt_txt": "2024-04-13 18:00:00"
        },
        {
            "dt": 1713042000,
            "main": {
                "temp": 77.99,
                "feels_like": 77.79,
                "temp_min": 77.99,
                "temp_max": 77.99,
                "pressure": 1021,
                "sea_level": 1021,
                "grnd_level": 1021,
                "humidity": 49,
                "temp_kf": 0
            },
            "weather": [
                {
                    "id": 800,
                    "main": "Clear",
                    "description": "clear sky",
                    "icon": "01d"
                }
            ],
            "clouds": {
                "all": 6
            },
            "wind": {
                "speed": 14.14,
                "deg": 64,
                "gust": 13.35
            },
            "visibility": 10000,
            "pop": 0,
            "sys": {
                "pod": "d"
            },
            "dt_txt": "2024-04-13 21:00:00"
        },
        {
            "dt": 1713052800,
            "main": {
                "temp": 75.31,
                "feels_like": 75.22,
                "temp_min": 75.31,
                "temp_max": 75.31,
                "pressure": 1022,
                "sea_level": 1022,
                "grnd_level": 1021,
                "humidity": 57,
                "temp_kf": 0
            },
            "weather": [
                {
                    "id": 800,
                    "main": "Clear",
                    "description": "clear sky",
                    "icon": "01n"
                }
            ],
            "clouds": {
                "all": 7
            },
            "wind": {
                "speed": 15.03,
                "deg": 59,
                "gust": 15.77
            },
            "visibility": 10000,
            "pop": 0,
            "sys": {
                "pod": "n"
            },
            "dt_txt": "2024-04-14 00:00:00"
        },
        {
            "dt": 1713063600,
            "main": {
                "temp": 74.21,
                "feels_like": 74.16,
                "temp_min": 74.21,
                "temp_max": 74.21,
                "pressure": 1022,
                "sea_level": 1022,
                "grnd_level": 1022,
                "humidity": 60,
                "temp_kf": 0
            },
            "weather": [
                {
                    "id": 803,
                    "main": "Clouds",
                    "description": "broken clouds",
                    "icon": "04n"
                }
            ],
            "clouds": {
                "all": 68
            },
            "wind": {
                "speed": 15.05,
                "deg": 68,
                "gust": 16.51
            },
            "visibility": 10000,
            "pop": 0,
            "sys": {
                "pod": "n"
            },
            "dt_txt": "2024-04-14 03:00:00"
        },
        {
            "dt": 1713074400,
            "main": {
                "temp": 73.45,
                "feels_like": 73.51,
                "temp_min": 73.45,
                "temp_max": 73.45,
                "pressure": 1021,
                "sea_level": 1021,
                "grnd_level": 1020,
                "humidity": 64,
                "temp_kf": 0
            },
            "weather": [
                {
                    "id": 802,
                    "main": "Clouds",
                    "description": "scattered clouds",
                    "icon": "03n"
                }
            ],
            "clouds": {
                "all": 40
            },
            "wind": {
                "speed": 12.55,
                "deg": 72,
                "gust": 14.34
            },
            "visibility": 10000,
            "pop": 0,
            "sys": {
                "pod": "n"
            },
            "dt_txt": "2024-04-14 06:00:00"
        },
        {
            "dt": 1713085200,
            "main": {
                "temp": 72.63,
                "feels_like": 72.46,
                "temp_min": 72.63,
                "temp_max": 72.63,
                "pressure": 1020,
                "sea_level": 1020,
                "grnd_level": 1020,
                "humidity": 61,
                "temp_kf": 0
            },
            "weather": [
                {
                    "id": 800,
                    "main": "Clear",
                    "description": "clear sky",
                    "icon": "01n"
                }
            ],
            "clouds": {
                "all": 8
            },
            "wind": {
                "speed": 12.03,
                "deg": 65,
                "gust": 13.18
            },
            "visibility": 10000,
            "pop": 0,
            "sys": {
                "pod": "n"
            },
            "dt_txt": "2024-04-14 09:00:00"
        },
        {
            "dt": 1713096000,
            "main": {
                "temp": 72.43,
                "feels_like": 72.23,
                "temp_min": 72.43,
                "temp_max": 72.43,
                "pressure": 1022,
                "sea_level": 1022,
                "grnd_level": 1021,
                "humidity": 61,
                "temp_kf": 0
            },
            "weather": [
                {
                    "id": 803,
                    "main": "Clouds",
                    "description": "broken clouds",
                    "icon": "04d"
                }
            ],
            "clouds": {
                "all": 55
            },
            "wind": {
                "speed": 12.39,
                "deg": 72,
                "gust": 13.56
            },
            "visibility": 10000,
            "pop": 0,
            "sys": {
                "pod": "d"
            },
            "dt_txt": "2024-04-14 12:00:00"
        }
    ],
    "city": {
        "id": 4151871,
        "name": "Coral Gables",
        "coord": {
            "lat": 25.7215,
            "lon": -80.2684
        },
        "country": "US",
        "population": 46780,
        "timezone": -14400,
        "sunrise": 1712660602,
        "sunset": 1712706071
    }
}